cding/__init__.py
cding/datasets/__init__.py
cding/datasets/coco.py
cding/file/__init__.py
cding/file/img.py
cding/file/json.py
cding/file/txt.py
cding/file/utils.py
cding/utils/__init__.py
cding/utils/time.py
cding/vis/__init__.py
cding/vis/draw.py
cding/vis/show.py
cding-0.0.6.dist-info/LICENSE
cding-0.0.6.dist-info/METADATA
cding-0.0.6.dist-info/WHEEL
cding-0.0.6.dist-info/top_level.txt
cding-0.0.6.dist-info/RECORD
