Metadata-Version: 2.1
Name: cding
Version: 0.0.6
Summary: A library with various functionality that can be useful.
Home-page: https://github.com/kevindingchan/cding
Author: ding chen
Author-email: kevindingchan@outlook.com
License: MIT
Platform: UNKNOWN
Classifier: Programming Language :: Python :: 3
Classifier: License :: OSI Approved :: MIT License
Classifier: Operating System :: OS Independent
Requires-Python: >=3.7
License-File: LICENSE
Requires-Dist: tqdm
Requires-Dist: opencv-python
Requires-Dist: pandas
Requires-Dist: matplotlib
Requires-Dist: pycocotools
